{"release_time": "2026-04-07T12:39:02+0800", "update_time": "2026-04-07T12:39:30+0800", "description": {"title": "豆瓣榜单", "subtitle": "美国恐怖片榜", "source": "https://m.douban.com/subject_collection/ECGMORRUY", "link": "https://m.douban.com/rexxar/api/v2/subject_collection/ECGMORRUY/items", "page_start": 1, "page_end": 1, "page_total": 1, "page_limit": -1, "item_total": 20, "item_limit": 20, "page_count": 1, "sup_page_count": 0}, "extra": {"subject_type": "movie", "id": "ECGMORRUY", "name": "美国恐怖片榜", "medium_name": "美国", "short_name": "恐怖片", "total": 20}, "stats": {"movies": 20}, "movies": [{"item_type": "movie", "id": "1417598", "rank": 1, "name": "电锯惊魂", "names": [], "links": ["https://movie.douban.com/subject/1417598/", "douban://douban.com/movie/1417598"], "covers": ["https://img9.doubanio.com/view/photo/m_ratio_poster/public/p726839485.jpg", "https://img9.doubanio.com/view/photo/s_ratio_poster/public/p726839485.jpg"], "rating": {"count": 614254, "max": 10, "star_count": 4.5, "value": 8.7}, "score": 8.7, "vote": 614254, "summary": "2004 / 美国 / 悬疑 惊悚 恐怖 / 温子仁 / 雷·沃纳尔 加利·艾尔维斯", "ext": {"comment": "", "controversy_reason": "", "rank_value": 1, "pic": {"large": "https://img9.doubanio.com/view/photo/m_ratio_poster/public/p726839485.jpg", "normal": "https://img9.doubanio.com/view/photo/s_ratio_poster/public/p726839485.jpg"}, "is_show": false, "vendor_icons": [], "has_linewatch": false, "is_released": true, "interest": null, "color_scheme": {"is_dark": true, "primary_color_light": "a5a399", "_base_color": [0.1372549019607844, 0.07623318385650223, 0.8745098039215686], "secondary_color": "f9f9f4", "_avg_color": [0.12962962962962973, 0.042056074766355124, 0.8392156862745098], "primary_color_dark": "7f7d75"}, "description": "", "tags": [], "cover_url": "https://img9.doubanio.com/view/photo/m_ratio_poster/public/p726839485.jpg", "photos": ["https://img2.doubanio.com/view/photo/m/public/p1677790721.jpg", "https://img3.doubanio.com/view/photo/m/public/p1677787027.jpg", "https://img9.doubanio.com/view/photo/m/public/p1688997366.jpg", "https://img9.doubanio.com/view/photo/m/public/p2514037524.jpg"], "actions": [], "sharing_url": "https://www.douban.com/doubanapp/dispatch/movie/1417598", "honor_infos": [{"kind": "movie", "uri": "douban://douban.com/subject_collection/movie_top250", "rank": 174, "title": "豆瓣电影Top250"}], "good_rating_stats": 0, "subtype": "movie", "null_rating_reason": ""}}, {"item_type": "movie", "id": "3011308", "rank": 2, "name": "孤儿怨", "names": [], "links": ["https://movie.douban.com/subject/3011308/", "douban://douban.com/movie/3011308"], "covers": ["https://img3.doubanio.com/view/photo/m_ratio_poster/public/p1592298962.jpg", "https://img3.doubanio.com/view/photo/s_ratio_poster/public/p1592298962.jpg"], "rating": {"count": 533214, "max": 10, "star_count": 4.0, "value": 8.2}, "score": 8.2, "vote": 533214, "summary": "2009 / 美国 加拿大 德国 法国 / 悬疑 惊悚 恐怖 / 佐米·希尔拉 / 维拉·法米加 彼得·萨斯加德", "ext": {"comment": "", "controversy_reason": "", "rank_value": 2, "pic": {"large": "https://img3.doubanio.com/view/photo/m_ratio_poster/public/p1592298962.jpg", "normal": "https://img3.doubanio.com/view/photo/s_ratio_poster/public/p1592298962.jpg"}, "is_show": false, "vendor_icons": ["https://img9.doubanio.com/f/frodo/fbc90f355fc45d5d2056e0d88c697f9414b56b44/pics/vendors/tencent.png", "https://img9.doubanio.com/f/frodo/6c7b857e6b2255201e73bf83732d95d572f3f9f7/pics/vendors/iqiyi.png"], "has_linewatch": true, "is_released": true, "interest": null, "color_scheme": {"is_dark": true, "primary_color_light": "5f7272", "_base_color": [0.5, 0.1694915254237288, 0.23137254901960785], "secondary_color": "f4f9f9", "_avg_color": [0.23333333333333361, 0.05050505050505047, 0.38823529411764707], "primary_color_dark": "3f4c4c"}, "description": "", "tags": [], "cover_url": "https://img3.doubanio.com/view/photo/m_ratio_poster/public/p1592298962.jpg", "photos": ["https://img1.doubanio.com/view/photo/m/public/p1570161839.jpg", "https://img3.doubanio.com/view/photo/m/public/p456911442.jpg", "https://img1.doubanio.com/view/photo/m/public/p456910679.jpg", "https://img3.doubanio.com/view/photo/m/public/p456910832.jpg"], "actions": ["可播放"], "sharing_url": "https://www.douban.com/doubanapp/dispatch/movie/3011308", "honor_infos": [{"kind": "movie", "uri": "douban://douban.com/subject_collection/film_genre_34?type=rank&category=movie&rank_type=film_genre", "rank": 3, "title": "评分最高恐怖片"}], "good_rating_stats": 0, "subtype": "movie", "null_rating_reason": ""}}, {"item_type": "movie", "id": "3804629", "rank": 3, "name": "招魂", "names": [], "links": ["https://movie.douban.com/subject/3804629/", "douban://douban.com/movie/3804629"], "covers": ["https://img3.doubanio.com/view/photo/m_ratio_poster/public/p1936517673.jpg", "https://img3.doubanio.com/view/photo/s_ratio_poster/public/p1936517673.jpg"], "rating": {"count": 401227, "max": 10, "star_count": 4.0, "value": 8.1}, "score": 8.1, "vote": 401227, "summary": "2013 / 美国 / 悬疑 惊悚 恐怖 / 温子仁 / 维拉·法米加 帕特里克·威尔森", "ext": {"comment": "", "controversy_reason": "", "rank_value": 3, "pic": {"large": "https://img3.doubanio.com/view/photo/m_ratio_poster/public/p1936517673.jpg", "normal": "https://img3.doubanio.com/view/photo/s_ratio_poster/public/p1936517673.jpg"}, "is_show": false, "vendor_icons": ["https://img2.doubanio.com/f/frodo/8e1b7f8b48804cf759fc411e75d62c5ffd4f8f42/pics/vendors/migu_video.png", "https://img9.doubanio.com/f/frodo/fbc90f355fc45d5d2056e0d88c697f9414b56b44/pics/vendors/tencent.png", "https://img9.doubanio.com/f/frodo/88a62f5e0cf9981c910e60f4421c3e66aac2c9bc/pics/vendors/bilibili.png"], "has_linewatch": true, "is_released": true, "interest": null, "color_scheme": {"is_dark": true, "primary_color_light": "a57b57", "_base_color": [0.07738095238095237, 0.4745762711864407, 0.23137254901960785], "secondary_color": "f9f7f4", "_avg_color": [0.07638888888888883, 0.1437125748502994, 0.6549019607843137], "primary_color_dark": "7f5f42"}, "description": "", "tags": [], "cover_url": "https://img3.doubanio.com/view/photo/m_ratio_poster/public/p1936517673.jpg", "photos": ["https://img1.doubanio.com/view/photo/m/public/p2016104019.jpg", "https://img3.doubanio.com/view/photo/m/public/p2016099412.jpg", "https://img9.doubanio.com/view/photo/m/public/p2016103535.jpg", "https://img1.doubanio.com/view/photo/m/public/p2016101018.jpg"], "actions": ["可播放"], "sharing_url": "https://www.douban.com/doubanapp/dispatch/movie/3804629", "honor_infos": [{"kind": "movie", "uri": "douban://douban.com/subject_collection/film_genre_34?type=rank&category=movie&rank_type=film_genre", "rank": 11, "title": "评分最高恐怖片"}], "good_rating_stats": 0, "subtype": "movie", "null_rating_reason": ""}}, {"item_type": "movie", "id": "1301459", "rank": 4, "name": "小岛惊魂", "names": [], "links": ["https://movie.douban.com/subject/1301459/", "douban://douban.com/movie/1301459"], "covers": ["https://img9.doubanio.com/view/photo/m_ratio_poster/public/p492298664.jpg", "https://img9.doubanio.com/view/photo/s_ratio_poster/public/p492298664.jpg"], "rating": {"count": 331876, "max": 10, "star_count": 4.0, "value": 8.2}, "score": 8.2, "vote": 331876, "summary": "2001 / 美国 西班牙 法国 意大利 / 剧情 悬疑 恐怖 / 亚历杭德罗·阿梅纳瓦尔 / 妮可·基德曼 菲奥纽拉·弗拉纳根", "ext": {"comment": "", "controversy_reason": "", "rank_value": 4, "pic": {"large": "https://img9.doubanio.com/view/photo/m_ratio_poster/public/p492298664.jpg", "normal": "https://img9.doubanio.com/view/photo/s_ratio_poster/public/p492298664.jpg"}, "is_show": false, "vendor_icons": ["https://img2.doubanio.com/f/frodo/8e1b7f8b48804cf759fc411e75d62c5ffd4f8f42/pics/vendors/migu_video.png", "https://img9.doubanio.com/f/frodo/fbc90f355fc45d5d2056e0d88c697f9414b56b44/pics/vendors/tencent.png", "https://img9.doubanio.com/f/frodo/88a62f5e0cf9981c910e60f4421c3e66aac2c9bc/pics/vendors/bilibili.png"], "has_linewatch": true, "is_released": true, "interest": null, "color_scheme": {"is_dark": true, "primary_color_light": "726969", "_base_color": [0.08, 0.09803921568627451], "secondary_color": "f9f4f4", "_avg_color": [0.05952380952380948, 0.2641509433962264, 0.20784313725490197], "primary_color_dark": "4c4646"}, "description": "", "tags": [], "cover_url": "https://img9.doubanio.com/view/photo/m_ratio_poster/public/p492298664.jpg", "photos": ["https://img1.doubanio.com/view/photo/m/public/p492302240.jpg", "https://img9.doubanio.com/view/photo/m/public/p492281366.jpg", "https://img3.doubanio.com/view/photo/m/public/p2506255933.jpg", "https://img1.doubanio.com/view/photo/m/public/p492302108.jpg"], "actions": ["可播放"], "sharing_url": "https://www.douban.com/doubanapp/dispatch/movie/1301459", "honor_infos": [{"kind": "movie", "uri": "douban://douban.com/subject_collection/film_genre_34?type=rank&category=movie&rank_type=film_genre", "rank": 9, "title": "评分最高恐怖片"}], "good_rating_stats": 0, "subtype": "movie", "null_rating_reason": ""}}, {"item_type": "movie", "id": "1945330", "rank": 5, "name": "迷雾", "names": [], "links": ["https://movie.douban.com/subject/1945330/", "douban://douban.com/movie/1945330"], "covers": ["https://img1.doubanio.com/view/photo/m_ratio_poster/public/p2363134750.jpg", "https://img1.doubanio.com/view/photo/s_ratio_poster/public/p2363134750.jpg"], "rating": {"count": 387647, "max": 10, "star_count": 4.0, "value": 8.1}, "score": 8.1, "vote": 387647, "summary": "2007 / 美国 / 科幻 惊悚 恐怖 / 弗兰克·德拉邦特 / 托马斯·简 马西娅·盖伊·哈登", "ext": {"comment": "", "controversy_reason": "", "rank_value": 5, "pic": {"large": "https://img1.doubanio.com/view/photo/m_ratio_poster/public/p2363134750.jpg", "normal": "https://img1.doubanio.com/view/photo/s_ratio_poster/public/p2363134750.jpg"}, "is_show": false, "vendor_icons": ["https://img9.doubanio.com/f/frodo/6c7b857e6b2255201e73bf83732d95d572f3f9f7/pics/vendors/iqiyi.png", "https://img3.doubanio.com/f/frodo/6fa5caade3ca480ccd95f455ee4d195ee342eb90/pics/vendors/youku.png"], "has_linewatch": true, "is_released": true, "interest": null, "color_scheme": {"is_dark": true, "primary_color_light": "726c62", "_base_color": [0.10416666666666659, 0.14479638009049772, 0.8666666666666667], "secondary_color": "f9f8f4", "_avg_color": [0.12318840579710148, 0.1900826446280991, 0.4745098039215686], "primary_color_dark": "4c4841"}, "description": "", "tags": [], "cover_url": "https://img1.doubanio.com/view/photo/m_ratio_poster/public/p2363134750.jpg", "photos": ["https://img3.doubanio.com/view/photo/m/public/p2271329722.jpg", "https://img2.doubanio.com/view/photo/m/public/p2153922511.jpg", "https://img9.doubanio.com/view/photo/m/public/p2153922406.jpg", "https://img3.doubanio.com/view/photo/m/public/p1510179687.jpg"], "actions": ["可播放"], "sharing_url": "https://www.douban.com/doubanapp/dispatch/movie/1945330", "honor_infos": [{"kind": "movie", "uri": "douban://douban.com/subject_collection/film_genre_34?type=rank&category=movie&rank_type=film_genre", "rank": 10, "title": "评分最高恐怖片"}], "good_rating_stats": 0, "subtype": "movie", "null_rating_reason": ""}}, {"item_type": "movie", "id": "1309045", "rank": 6, "name": "电锯惊魂2", "names": [], "links": ["https://movie.douban.com/subject/1309045/", "douban://douban.com/movie/1309045"], "covers": ["https://img1.doubanio.com/view/photo/m_ratio_poster/public/p1421210839.jpg", "https://img1.doubanio.com/view/photo/s_ratio_poster/public/p1421210839.jpg"], "rating": {"count": 250808, "max": 10, "star_count": 4.0, "value": 8.4}, "score": 8.4, "vote": 250808, "summary": "2005 / 美国 加拿大 / 悬疑 惊悚 恐怖 / 达伦·林恩·鲍斯曼 / 托宾·贝尔 肖妮·史密斯", "ext": {"comment": "", "controversy_reason": "", "rank_value": 6, "pic": {"large": "https://img1.doubanio.com/view/photo/m_ratio_poster/public/p1421210839.jpg", "normal": "https://img1.doubanio.com/view/photo/s_ratio_poster/public/p1421210839.jpg"}, "is_show": false, "vendor_icons": [], "has_linewatch": false, "is_released": true, "interest": null, "color_scheme": {"is_dark": true, "primary_color_light": "a5874f", "_base_color": [0.10897435897435899, 0.52, 0.19607843137254902], "secondary_color": "f9f8f4", "_avg_color": [0.11666666666666664, 0.11627906976744193, 0.6745098039215687], "primary_color_dark": "7f683d"}, "description": "", "tags": [], "cover_url": "https://img1.doubanio.com/view/photo/m_ratio_poster/public/p1421210839.jpg", "photos": ["https://img9.doubanio.com/view/photo/m/public/p443443075.jpg", "https://img2.doubanio.com/view/photo/m/public/p443443091.jpg", "https://img3.doubanio.com/view/photo/m/public/p443443037.jpg", "https://img3.doubanio.com/view/photo/m/public/p443442873.jpg"], "actions": [], "sharing_url": "https://www.douban.com/doubanapp/dispatch/movie/1309045", "honor_infos": [{"kind": "movie", "uri": "douban://douban.com/subject_collection/film_genre_34?type=rank&category=movie&rank_type=film_genre", "rank": 6, "title": "评分最高恐怖片"}], "good_rating_stats": 0, "subtype": "movie", "null_rating_reason": ""}}, {"item_type": "movie", "id": "1418752", "rank": 7, "name": "万能钥匙", "names": [], "links": ["https://movie.douban.com/subject/1418752/", "douban://douban.com/movie/1418752"], "covers": ["https://img3.doubanio.com/view/photo/m_ratio_poster/public/p810384382.jpg", "https://img3.doubanio.com/view/photo/s_ratio_poster/public/p810384382.jpg"], "rating": {"count": 418328, "max": 10, "star_count": 4.0, "value": 8.0}, "score": 8.0, "vote": 418328, "summary": "2005 / 美国 德国 / 剧情 悬疑 恐怖 / 伊恩·索夫特雷 / 凯特·哈德森 吉娜·罗兰兹", "ext": {"comment": "", "controversy_reason": "", "rank_value": 7, "pic": {"large": "https://img3.doubanio.com/view/photo/m_ratio_poster/public/p810384382.jpg", "normal": "https://img3.doubanio.com/view/photo/s_ratio_poster/public/p810384382.jpg"}, "is_show": false, "vendor_icons": ["https://img9.doubanio.com/f/frodo/fbc90f355fc45d5d2056e0d88c697f9414b56b44/pics/vendors/tencent.png", "https://img3.doubanio.com/f/frodo/6fa5caade3ca480ccd95f455ee4d195ee342eb90/pics/vendors/youku.png", "https://img9.doubanio.com/f/frodo/6c7b857e6b2255201e73bf83732d95d572f3f9f7/pics/vendors/iqiyi.png"], "has_linewatch": true, "is_released": true, "interest": null, "color_scheme": {"is_dark": true, "primary_color_light": "a4a5a4", "_base_color": [0.3333333333333333, 0.009049773755656205, 0.8666666666666667], "secondary_color": "f4f9f4", "_avg_color": [0.27777777777777773, 0.019480519480519414, 0.6039215686274509], "primary_color_dark": "7e7f7e"}, "description": "", "tags": [], "cover_url": "https://img3.doubanio.com/view/photo/m_ratio_poster/public/p810384382.jpg", "photos": ["https://img3.doubanio.com/view/photo/m/public/p547284073.jpg", "https://img9.doubanio.com/view/photo/m/public/p547283816.jpg", "https://img3.doubanio.com/view/photo/m/public/p547283923.jpg", "https://img1.doubanio.com/view/photo/m/public/p547283449.jpg"], "actions": ["可播放"], "sharing_url": "https://www.douban.com/doubanapp/dispatch/movie/1418752", "honor_infos": [{"kind": "movie", "uri": "douban://douban.com/subject_collection/film_genre_34?type=rank&category=movie&rank_type=film_genre", "rank": 7, "title": "评分最高恐怖片"}], "good_rating_stats": 0, "subtype": "movie", "null_rating_reason": ""}}, {"item_type": "movie", "id": "1300300", "rank": 8, "name": "死神来了", "names": [], "links": ["https://movie.douban.com/subject/1300300/", "douban://douban.com/movie/1300300"], "covers": ["https://img9.doubanio.com/view/photo/m_ratio_poster/public/p2867790676.jpg", "https://img9.doubanio.com/view/photo/s_ratio_poster/public/p2867790676.jpg"], "rating": {"count": 387943, "max": 10, "star_count": 4.0, "value": 7.9}, "score": 7.9, "vote": 387943, "summary": "2000 / 美国 加拿大 / 惊悚 恐怖 / 黄毅瑜 / 戴文·萨瓦 艾丽·拉特", "ext": {"comment": "", "controversy_reason": "", "rank_value": 8, "pic": {"large": "https://img9.doubanio.com/view/photo/m_ratio_poster/public/p2867790676.jpg", "normal": "https://img9.doubanio.com/view/photo/s_ratio_poster/public/p2867790676.jpg"}, "is_show": false, "vendor_icons": [], "has_linewatch": false, "is_released": true, "interest": null, "color_scheme": {"is_dark": true, "primary_color_light": "585b72", "_base_color": [0.6458333333333334, 0.22857142857142865, 0.13725490196078433], "secondary_color": "f4f5f9", "_avg_color": [0.7000000000000001, 0.08771929824561409, 0.2235294117647059], "primary_color_dark": "3b3d4c"}, "description": "", "tags": [], "cover_url": "https://img9.doubanio.com/view/photo/m_ratio_poster/public/p2867790676.jpg", "photos": ["https://img9.doubanio.com/view/photo/m/public/p458249306.jpg", "https://img2.doubanio.com/view/photo/m/public/p458247151.jpg", "https://img9.doubanio.com/view/photo/m/public/p458248576.jpg", "https://img3.doubanio.com/view/photo/m/public/p458248312.jpg"], "actions": [], "sharing_url": "https://www.douban.com/doubanapp/dispatch/movie/1300300", "honor_infos": [{"kind": "movie", "uri": "douban://douban.com/subject_collection/film_genre_34?type=rank&category=movie&rank_type=film_genre", "rank": 12, "title": "评分最高恐怖片"}], "good_rating_stats": 0, "subtype": "movie", "null_rating_reason": ""}}, {"item_type": "movie", "id": "26688480", "rank": 9, "name": "逃出绝命镇", "names": [], "links": ["https://movie.douban.com/subject/26688480/", "douban://douban.com/movie/26688480"], "covers": ["https://img2.doubanio.com/view/photo/m_ratio_poster/public/p2508604641.jpg", "https://img2.doubanio.com/view/photo/s_ratio_poster/public/p2508604641.jpg"], "rating": {"count": 442711, "max": 10, "star_count": 4.0, "value": 7.8}, "score": 7.8, "vote": 442711, "summary": "2017 / 美国 / 悬疑 惊悚 恐怖 / 乔丹·皮尔 / 丹尼尔·卡卢亚 艾莉森·威廉姆斯", "ext": {"comment": "", "controversy_reason": "", "rank_value": 9, "pic": {"large": "https://img2.doubanio.com/view/photo/m_ratio_poster/public/p2508604641.jpg", "normal": "https://img2.doubanio.com/view/photo/s_ratio_poster/public/p2508604641.jpg"}, "is_show": false, "vendor_icons": ["https://img2.doubanio.com/f/frodo/8e1b7f8b48804cf759fc411e75d62c5ffd4f8f42/pics/vendors/migu_video.png", "https://img9.doubanio.com/f/frodo/fbc90f355fc45d5d2056e0d88c697f9414b56b44/pics/vendors/tencent.png", "https://img9.doubanio.com/f/frodo/6c7b857e6b2255201e73bf83732d95d572f3f9f7/pics/vendors/iqiyi.png"], "has_linewatch": true, "is_released": true, "interest": null, "color_scheme": {"is_dark": true, "primary_color_light": "5d6c72", "_base_color": [0.5476190476190476, 0.18918918918918926, 0.1450980392156863], "secondary_color": "f4f8f9", "_avg_color": [0.5555555555555555, 0.16901408450704225, 0.2784313725490196], "primary_color_dark": "3e484c"}, "description": "", "tags": [], "cover_url": "https://img2.doubanio.com/view/photo/m_ratio_poster/public/p2508604641.jpg", "photos": ["https://img1.doubanio.com/view/photo/m/public/p2458854169.jpg", "https://img9.doubanio.com/view/photo/m/public/p2458265264.jpg", "https://img1.doubanio.com/view/photo/m/public/p2434271480.jpg", "https://img9.doubanio.com/view/photo/m/public/p2458265156.jpg"], "actions": ["可播放"], "sharing_url": "https://www.douban.com/doubanapp/dispatch/movie/26688480", "honor_infos": [{"kind": "movie", "uri": "douban://douban.com/subject_collection/film_genre_34?type=rank&category=movie&rank_type=film_genre", "rank": 14, "title": "评分最高恐怖片"}], "good_rating_stats": 0, "subtype": "movie", "null_rating_reason": ""}}, {"item_type": "movie", "id": "1895120", "rank": 10, "name": "死寂", "names": [], "links": ["https://movie.douban.com/subject/1895120/", "douban://douban.com/movie/1895120"], "covers": ["https://img1.doubanio.com/view/photo/m_ratio_poster/public/p1235830609.jpg", "https://img1.doubanio.com/view/photo/s_ratio_poster/public/p1235830609.jpg"], "rating": {"count": 332353, "max": 10, "star_count": 4.0, "value": 7.9}, "score": 7.9, "vote": 332353, "summary": "2007 / 美国 / 悬疑 恐怖 / 温子仁 / 唐尼·沃尔伯格 安贝·瓦莱塔", "ext": {"comment": "", "controversy_reason": "", "rank_value": 10, "pic": {"large": "https://img1.doubanio.com/view/photo/m_ratio_poster/public/p1235830609.jpg", "normal": "https://img1.doubanio.com/view/photo/s_ratio_poster/public/p1235830609.jpg"}, "is_show": false, "vendor_icons": ["https://img9.doubanio.com/f/frodo/fbc90f355fc45d5d2056e0d88c697f9414b56b44/pics/vendors/tencent.png", "https://img9.doubanio.com/f/frodo/6c7b857e6b2255201e73bf83732d95d572f3f9f7/pics/vendors/iqiyi.png", "https://img9.doubanio.com/f/frodo/88a62f5e0cf9981c910e60f4421c3e66aac2c9bc/pics/vendors/bilibili.png"], "has_linewatch": true, "is_released": true, "interest": null, "color_scheme": {"is_dark": true, "primary_color_light": "72372e", "_base_color": [0.020833333333333332, 0.5925925925925926, 0.10588235294117647], "secondary_color": "f9f5f4", "_avg_color": [0.027777777777777752, 0.4225352112676056, 0.2784313725490196], "primary_color_dark": "4c241f"}, "description": "", "tags": [], "cover_url": "https://img1.doubanio.com/view/photo/m_ratio_poster/public/p1235830609.jpg", "photos": ["https://img9.doubanio.com/view/photo/m/public/p568818515.jpg", "https://img9.doubanio.com/view/photo/m/public/p568832655.jpg", "https://img9.doubanio.com/view/photo/m/public/p568814875.jpg", "https://img1.doubanio.com/view/photo/m/public/p568812369.jpg"], "actions": ["可播放"], "sharing_url": "https://www.douban.com/doubanapp/dispatch/movie/1895120", "honor_infos": [{"kind": "movie", "uri": "douban://douban.com/subject_collection/film_genre_34?type=rank&category=movie&rank_type=film_genre", "rank": 20, "title": "评分最高恐怖片"}], "good_rating_stats": 0, "subtype": "movie", "null_rating_reason": ""}}, {"item_type": "movie", "id": "2132473", "rank": 11, "name": "僵尸世界大战", "names": [], "links": ["https://movie.douban.com/subject/2132473/", "douban://douban.com/movie/2132473"], "covers": ["https://img3.doubanio.com/view/photo/m_ratio_poster/public/p2211899397.jpg", "https://img3.doubanio.com/view/photo/s_ratio_poster/public/p2211899397.jpg"], "rating": {"count": 349631, "max": 10, "star_count": 4.0, "value": 7.7}, "score": 7.7, "vote": 349631, "summary": "2013 / 美国 英国 马耳他 / 动作 科幻 恐怖 / 马克·福斯特 / 布拉德·皮特 米瑞·伊诺丝", "ext": {"comment": "", "controversy_reason": "", "rank_value": 11, "pic": {"large": "https://img3.doubanio.com/view/photo/m_ratio_poster/public/p2211899397.jpg", "normal": "https://img3.doubanio.com/view/photo/s_ratio_poster/public/p2211899397.jpg"}, "is_show": false, "vendor_icons": ["https://img9.doubanio.com/f/frodo/fbc90f355fc45d5d2056e0d88c697f9414b56b44/pics/vendors/tencent.png", "https://img2.doubanio.com/f/frodo/8e1b7f8b48804cf759fc411e75d62c5ffd4f8f42/pics/vendors/migu_video.png", "https://img9.doubanio.com/f/frodo/6c7b857e6b2255201e73bf83732d95d572f3f9f7/pics/vendors/iqiyi.png"], "has_linewatch": true, "is_released": true, "interest": null, "color_scheme": {"is_dark": true, "primary_color_light": "72706d", "_base_color": [0.09259259259259282, 0.04147465437788017, 0.8509803921568627], "secondary_color": "f9f7f4", "_avg_color": [0.4166666666666667, 0.016666666666666607, 0.47058823529411764], "primary_color_dark": "4c4b49"}, "description": "", "tags": [], "cover_url": "https://img3.doubanio.com/view/photo/m_ratio_poster/public/p2211899397.jpg", "photos": ["https://img1.doubanio.com/view/photo/m/public/p2016154060.jpg", "https://img3.doubanio.com/view/photo/m/public/p2458097743.jpg", "https://img9.doubanio.com/view/photo/m/public/p2016153576.jpg", "https://img3.doubanio.com/view/photo/m/public/p2016159932.jpg"], "actions": ["可播放"], "sharing_url": "https://www.douban.com/doubanapp/dispatch/movie/2132473", "honor_infos": [{"kind": "movie", "uri": "douban://douban.com/subject_collection/EC6EPQIKA?type=rank&category=movie&rank_type=film_genre", "rank": 6, "title": "高分僵尸电影榜"}], "good_rating_stats": 0, "subtype": "movie", "null_rating_reason": ""}}, {"item_type": "movie", "id": "26725678", "rank": 12, "name": "解除好友2：暗网", "names": [], "links": ["https://movie.douban.com/subject/26725678/", "douban://douban.com/movie/26725678"], "covers": ["https://img2.doubanio.com/view/photo/m_ratio_poster/public/p2528012421.jpg", "https://img2.doubanio.com/view/photo/s_ratio_poster/public/p2528012421.jpg"], "rating": {"count": 231899, "max": 10, "star_count": 4.0, "value": 7.9}, "score": 7.9, "vote": 231899, "summary": "2018 / 美国 / 恐怖 犯罪 / 斯蒂芬·苏斯科 / 科林·伍德尔 斯蒂芬妮·诺格拉斯", "ext": {"comment": "", "controversy_reason": "", "rank_value": 12, "pic": {"large": "https://img2.doubanio.com/view/photo/m_ratio_poster/public/p2528012421.jpg", "normal": "https://img2.doubanio.com/view/photo/s_ratio_poster/public/p2528012421.jpg"}, "is_show": false, "vendor_icons": ["https://img9.doubanio.com/f/frodo/fbc90f355fc45d5d2056e0d88c697f9414b56b44/pics/vendors/tencent.png", "https://img3.doubanio.com/f/frodo/6fa5caade3ca480ccd95f455ee4d195ee342eb90/pics/vendors/youku.png", "https://img9.doubanio.com/f/frodo/88a62f5e0cf9981c910e60f4421c3e66aac2c9bc/pics/vendors/bilibili.png"], "has_linewatch": true, "is_released": true, "interest": null, "color_scheme": {"is_dark": true, "primary_color_light": "1c3972", "_base_color": [0.6111111111111112, 0.75, 0.09411764705882353], "secondary_color": "f4f6f9", "_avg_color": [0.5833333333333334, 0.6363636363636364, 0.17254901960784313], "primary_color_dark": "13264c"}, "description": "", "tags": [], "cover_url": "https://img2.doubanio.com/view/photo/m_ratio_poster/public/p2528012421.jpg", "photos": ["https://img1.doubanio.com/view/photo/m/public/p2533958190.jpg", "https://img1.doubanio.com/view/photo/m/public/p2574038708.jpg", "https://img3.doubanio.com/view/photo/m/public/p2535831227.jpg", "https://img2.doubanio.com/view/photo/m/public/p2533958201.jpg"], "actions": ["可播放"], "sharing_url": "https://www.douban.com/doubanapp/dispatch/movie/26725678", "honor_infos": [{"kind": "movie", "uri": "douban://douban.com/subject_collection/film_genre_34?type=rank&category=movie&rank_type=film_genre", "rank": 15, "title": "评分最高恐怖片"}], "good_rating_stats": 0, "subtype": "movie", "null_rating_reason": ""}}, {"item_type": "movie", "id": "10485526", "rank": 13, "name": "潜伏2", "names": [], "links": ["https://movie.douban.com/subject/10485526/", "douban://douban.com/movie/10485526"], "covers": ["https://img1.doubanio.com/view/photo/m_ratio_poster/public/p2044151740.jpg", "https://img1.doubanio.com/view/photo/s_ratio_poster/public/p2044151740.jpg"], "rating": {"count": 142235, "max": 10, "star_count": 4.0, "value": 8.2}, "score": 8.2, "vote": 142235, "summary": "2013 / 美国 加拿大 / 惊悚 恐怖 / 温子仁 / 帕特里克·威尔森 萝丝·拜恩", "ext": {"comment": "", "controversy_reason": "", "rank_value": 13, "pic": {"large": "https://img1.doubanio.com/view/photo/m_ratio_poster/public/p2044151740.jpg", "normal": "https://img1.doubanio.com/view/photo/s_ratio_poster/public/p2044151740.jpg"}, "is_show": false, "vendor_icons": [], "has_linewatch": false, "is_released": true, "interest": null, "color_scheme": {"is_dark": true, "primary_color_light": "727272", "_base_color": [0.050980392156862744], "secondary_color": "f9f4f4", "_avg_color": [0.06451612903225806, 0.12156862745098039], "primary_color_dark": "4c4c4c"}, "description": "", "tags": [], "cover_url": "https://img1.doubanio.com/view/photo/m_ratio_poster/public/p2044151740.jpg", "photos": ["https://img1.doubanio.com/view/photo/m/public/p2111211770.jpg", "https://img1.doubanio.com/view/photo/m/public/p2111216388.jpg", "https://img9.doubanio.com/view/photo/m/public/p2111474996.jpg", "https://img9.doubanio.com/view/photo/m/public/p2111243316.jpg"], "actions": [], "sharing_url": "https://www.douban.com/doubanapp/dispatch/movie/10485526", "honor_infos": [{"kind": "movie", "uri": "douban://douban.com/subject_collection/ECOQPPT4A?type=rank&category=movie&rank_type=film_genre", "rank": 7, "title": "高分灵异电影榜"}], "good_rating_stats": 0, "subtype": "movie", "null_rating_reason": ""}}, {"item_type": "movie", "id": "4817901", "rank": 14, "name": "潜伏", "names": [], "links": ["https://movie.douban.com/subject/4817901/", "douban://douban.com/movie/4817901"], "covers": ["https://img9.doubanio.com/view/photo/m_ratio_poster/public/p919571676.jpg", "https://img9.doubanio.com/view/photo/s_ratio_poster/public/p919571676.jpg"], "rating": {"count": 193020, "max": 10, "star_count": 4.0, "value": 7.9}, "score": 7.9, "vote": 193020, "summary": "2010 / 美国 加拿大 / 惊悚 恐怖 / 温子仁 / 萝丝·拜恩 帕特里克·威尔森", "ext": {"comment": "", "controversy_reason": "", "rank_value": 14, "pic": {"large": "https://img9.doubanio.com/view/photo/m_ratio_poster/public/p919571676.jpg", "normal": "https://img9.doubanio.com/view/photo/s_ratio_poster/public/p919571676.jpg"}, "is_show": false, "vendor_icons": ["https://img9.doubanio.com/f/frodo/fbc90f355fc45d5d2056e0d88c697f9414b56b44/pics/vendors/tencent.png"], "has_linewatch": true, "is_released": true, "interest": null, "color_scheme": {"is_dark": true, "primary_color_light": "567266", "_base_color": [0.4270833333333333, 0.25, 0.25098039215686274], "secondary_color": "f4f9f7", "_avg_color": [0.4270833333333333, 0.19512195121951217, 0.3215686274509804], "primary_color_dark": "394c44"}, "description": "", "tags": [], "cover_url": "https://img9.doubanio.com/view/photo/m_ratio_poster/public/p919571676.jpg", "photos": ["https://img3.doubanio.com/view/photo/m/public/p933879412.jpg", "https://img3.doubanio.com/view/photo/m/public/p607330522.jpg", "https://img2.doubanio.com/view/photo/m/public/p933877091.jpg", "https://img9.doubanio.com/view/photo/m/public/p933878715.jpg"], "actions": ["可播放"], "sharing_url": "https://www.douban.com/doubanapp/dispatch/movie/4817901", "honor_infos": [{"kind": "movie", "uri": "douban://douban.com/subject_collection/ECOQPPT4A?type=rank&category=movie&rank_type=film_genre", "rank": 8, "title": "高分灵异电影榜"}], "good_rating_stats": 0, "subtype": "movie", "null_rating_reason": ""}}, {"item_type": "movie", "id": "35792500", "rank": 15, "name": "异形：夺命舰", "names": [], "links": ["https://movie.douban.com/subject/35792500/", "douban://douban.com/movie/35792500"], "covers": ["https://img9.doubanio.com/view/photo/m_ratio_poster/public/p2910926865.jpg", "https://img9.doubanio.com/view/photo/s_ratio_poster/public/p2910926865.jpg"], "rating": {"count": 383899, "max": 10, "star_count": 3.5, "value": 7.3}, "score": 7.3, "vote": 383899, "summary": "2024 / 美国 英国 / 科幻 惊悚 恐怖 / 费德·阿尔瓦雷兹 / 卡莉·史派妮 戴维·荣松", "ext": {"comment": "", "controversy_reason": "", "rank_value": 15, "pic": {"large": "https://img9.doubanio.com/view/photo/m_ratio_poster/public/p2910926865.jpg", "normal": "https://img9.doubanio.com/view/photo/s_ratio_poster/public/p2910926865.jpg"}, "is_show": false, "vendor_icons": ["https://img9.doubanio.com/f/frodo/fbc90f355fc45d5d2056e0d88c697f9414b56b44/pics/vendors/tencent.png", "https://img2.doubanio.com/f/frodo/8e1b7f8b48804cf759fc411e75d62c5ffd4f8f42/pics/vendors/migu_video.png", "https://img9.doubanio.com/f/frodo/6c7b857e6b2255201e73bf83732d95d572f3f9f7/pics/vendors/iqiyi.png"], "has_linewatch": true, "is_released": true, "interest": null, "color_scheme": {"is_dark": true, "primary_color_light": "724d37", "_base_color": [0.06140350877192983, 0.516304347826087, 0.7215686274509804], "secondary_color": "f9f6f4", "_avg_color": [0.05333333333333332, 0.42372881355932207, 0.23137254901960785], "primary_color_dark": "4c3325"}, "description": "", "tags": [], "cover_url": "https://img9.doubanio.com/view/photo/m_ratio_poster/public/p2910926865.jpg", "photos": ["https://img3.doubanio.com/view/photo/m/public/p2905901513.jpg", "https://img3.doubanio.com/view/photo/m/public/p2905901517.jpg", "https://img9.doubanio.com/view/photo/m/public/p2905901516.jpg", "https://img1.doubanio.com/view/photo/m/public/p2910800040.jpg"], "actions": ["可播放"], "sharing_url": "https://www.douban.com/doubanapp/dispatch/movie/35792500", "honor_infos": [{"kind": "movie", "uri": "douban://douban.com/subject_collection/ECV4N4FBI?type=rank&category=movie&rank_type=film_genre", "rank": 2, "title": "近期热门恐怖片榜"}], "good_rating_stats": 0, "subtype": "movie", "null_rating_reason": ""}}, {"item_type": "movie", "id": "3604148", "rank": 16, "name": "小丑回魂", "names": [], "links": ["https://movie.douban.com/subject/3604148/", "douban://douban.com/movie/3604148"], "covers": ["https://img9.doubanio.com/view/photo/m_ratio_poster/public/p2452537144.jpg", "https://img9.doubanio.com/view/photo/s_ratio_poster/public/p2452537144.jpg"], "rating": {"count": 227458, "max": 10, "star_count": 4.0, "value": 7.5}, "score": 7.5, "vote": 227458, "summary": "2017 / 美国 加拿大 / 剧情 恐怖 / 安德斯·穆斯切蒂 / 比尔·斯卡斯加德 杰登·马泰尔", "ext": {"comment": "", "controversy_reason": "", "rank_value": 16, "pic": {"large": "https://img9.doubanio.com/view/photo/m_ratio_poster/public/p2452537144.jpg", "normal": "https://img9.doubanio.com/view/photo/s_ratio_poster/public/p2452537144.jpg"}, "is_show": false, "vendor_icons": [], "has_linewatch": false, "is_released": true, "interest": null, "color_scheme": {"is_dark": true, "primary_color_light": "726d67", "_base_color": [0.08333333333333333, 0.1, 0.0784313725490196], "secondary_color": "f9f7f4", "_avg_color": [0.07575757575757573, 0.31428571428571433, 0.13725490196078433], "primary_color_dark": "4c4844"}, "description": "", "tags": [], "cover_url": "https://img9.doubanio.com/view/photo/m_ratio_poster/public/p2452537144.jpg", "photos": ["https://img1.doubanio.com/view/photo/m/public/p2499399150.jpg", "https://img2.doubanio.com/view/photo/m/public/p2497386641.jpg", "https://img2.doubanio.com/view/photo/m/public/p2497386601.jpg", "https://img1.doubanio.com/view/photo/m/public/p2499609380.jpg"], "actions": [], "sharing_url": "https://www.douban.com/doubanapp/dispatch/movie/3604148", "honor_infos": [{"kind": "movie", "uri": "douban://douban.com/subject_collection/ECGMORRUY?type=rank&category=movie&rank_type=film_genre", "rank": 16, "title": "美国恐怖片榜"}], "good_rating_stats": 0, "subtype": "movie", "null_rating_reason": ""}}, {"item_type": "movie", "id": "1793903", "rank": 17, "name": "幻影凶间", "names": [], "links": ["https://movie.douban.com/subject/1793903/", "douban://douban.com/movie/1793903"], "covers": ["https://img1.doubanio.com/view/photo/m_ratio_poster/public/p887024730.jpg", "https://img1.doubanio.com/view/photo/s_ratio_poster/public/p887024730.jpg"], "rating": {"count": 184923, "max": 10, "star_count": 4.0, "value": 7.6}, "score": 7.6, "vote": 184923, "summary": "2007 / 美国 / 悬疑 恐怖 奇幻 / 米凯尔·哈弗斯特罗姆 / 约翰·库萨克 塞缪尔·杰克逊", "ext": {"comment": "", "controversy_reason": "", "rank_value": 17, "pic": {"large": "https://img1.doubanio.com/view/photo/m_ratio_poster/public/p887024730.jpg", "normal": "https://img1.doubanio.com/view/photo/s_ratio_poster/public/p887024730.jpg"}, "is_show": false, "vendor_icons": [], "has_linewatch": false, "is_released": true, "interest": null, "color_scheme": {"is_dark": true, "primary_color_light": "722c12", "_base_color": [0.045138888888888874, 0.8421052631578947, 0.2235294117647059], "secondary_color": "f9f6f4", "_avg_color": [0.08208955223880594, 0.6767676767676768, 0.38823529411764707], "primary_color_dark": "4c1d0c"}, "description": "", "tags": [], "cover_url": "https://img1.doubanio.com/view/photo/m_ratio_poster/public/p887024730.jpg", "photos": ["https://img3.doubanio.com/view/photo/m/public/p443318492.jpg", "https://img3.doubanio.com/view/photo/m/public/p443318567.jpg", "https://img3.doubanio.com/view/photo/m/public/p443318437.jpg", "https://img2.doubanio.com/view/photo/m/public/p443318381.jpg"], "actions": [], "sharing_url": "https://www.douban.com/doubanapp/dispatch/movie/1793903", "honor_infos": [{"kind": "movie", "uri": "douban://douban.com/subject_collection/ECOQPPT4A?type=rank&category=movie&rank_type=film_genre", "rank": 10, "title": "高分灵异电影榜"}], "good_rating_stats": 0, "subtype": "movie", "null_rating_reason": ""}}, {"item_type": "movie", "id": "1293852", "rank": 18, "name": "罗斯玛丽的婴儿", "names": [], "links": ["https://movie.douban.com/subject/1293852/", "douban://douban.com/movie/1293852"], "covers": ["https://img3.doubanio.com/view/photo/m_ratio_poster/public/p2517730337.jpg", "https://img3.doubanio.com/view/photo/s_ratio_poster/public/p2517730337.jpg"], "rating": {"count": 88850, "max": 10, "star_count": 4.0, "value": 8.2}, "score": 8.2, "vote": 88850, "summary": "1968 / 美国 / 剧情 恐怖 / 罗曼·波兰斯基 / 米娅·法罗 约翰·卡萨韦蒂斯", "ext": {"comment": "", "controversy_reason": "", "rank_value": 18, "pic": {"large": "https://img3.doubanio.com/view/photo/m_ratio_poster/public/p2517730337.jpg", "normal": "https://img3.doubanio.com/view/photo/s_ratio_poster/public/p2517730337.jpg"}, "is_show": false, "vendor_icons": ["https://img9.doubanio.com/f/frodo/fbc90f355fc45d5d2056e0d88c697f9414b56b44/pics/vendors/tencent.png", "https://img2.doubanio.com/f/frodo/8e1b7f8b48804cf759fc411e75d62c5ffd4f8f42/pics/vendors/migu_video.png", "https://img9.doubanio.com/f/frodo/88a62f5e0cf9981c910e60f4421c3e66aac2c9bc/pics/vendors/bilibili.png"], "has_linewatch": true, "is_released": true, "interest": null, "color_scheme": {"is_dark": true, "primary_color_light": "5a7264", "_base_color": [0.4000000000000001, 0.2083333333333333, 0.2823529411764706], "secondary_color": "f4f9f6", "_avg_color": [0.39393939393939403, 0.10476190476190467, 0.4117647058823529], "primary_color_dark": "3c4c42"}, "description": "", "tags": [], "cover_url": "https://img3.doubanio.com/view/photo/m_ratio_poster/public/p2517730337.jpg", "photos": ["https://img1.doubanio.com/view/photo/m/public/p580714100.jpg", "https://img1.doubanio.com/view/photo/m/public/p2506365120.jpg", "https://img3.doubanio.com/view/photo/m/public/p457157043.jpg", "https://img3.doubanio.com/view/photo/m/public/p2360359677.jpg"], "actions": ["可播放"], "sharing_url": "https://www.douban.com/doubanapp/dispatch/movie/1293852", "honor_infos": [{"kind": "movie", "uri": "douban://douban.com/subject_collection/ECGMORRUY?type=rank&category=movie&rank_type=film_genre", "rank": 18, "title": "美国恐怖片榜"}], "good_rating_stats": 0, "subtype": "movie", "null_rating_reason": ""}}, {"item_type": "movie", "id": "27621727", "rank": 19, "name": "遗传厄运", "names": [], "links": ["https://movie.douban.com/subject/27621727/", "douban://douban.com/movie/27621727"], "covers": ["https://img3.doubanio.com/view/photo/m_ratio_poster/public/p2518865763.jpg", "https://img3.doubanio.com/view/photo/s_ratio_poster/public/p2518865763.jpg"], "rating": {"count": 195401, "max": 10, "star_count": 3.5, "value": 7.4}, "score": 7.4, "vote": 195401, "summary": "2018 / 美国 / 恐怖 / 阿里·艾斯特 / 亚历克斯·沃尔夫 加布里埃尔·伯恩", "ext": {"comment": "", "controversy_reason": "", "rank_value": 19, "pic": {"large": "https://img3.doubanio.com/view/photo/m_ratio_poster/public/p2518865763.jpg", "normal": "https://img3.doubanio.com/view/photo/s_ratio_poster/public/p2518865763.jpg"}, "is_show": false, "vendor_icons": [], "has_linewatch": false, "is_released": true, "interest": null, "color_scheme": {"is_dark": true, "primary_color_light": "647272", "_base_color": [0.5, 0.125, 0.12549019607843137], "secondary_color": "f4f9f9", "_avg_color": [0.5, 0.08333333333333323, 0.1411764705882353], "primary_color_dark": "424c4c"}, "description": "", "tags": [], "cover_url": "https://img3.doubanio.com/view/photo/m_ratio_poster/public/p2518865763.jpg", "photos": ["https://img9.doubanio.com/view/photo/m/public/p2520010404.jpg", "https://img1.doubanio.com/view/photo/m/public/p2523060229.jpg", "https://img3.doubanio.com/view/photo/m/public/p2523060253.jpg", "https://img1.doubanio.com/view/photo/m/public/p2512249058.jpg"], "actions": [], "sharing_url": "https://www.douban.com/doubanapp/dispatch/movie/27621727", "honor_infos": [{"kind": "movie", "uri": "douban://douban.com/subject_collection/ECOQPPT4A?type=rank&category=movie&rank_type=film_genre", "rank": 16, "title": "高分灵异电影榜"}], "good_rating_stats": 0, "subtype": "movie", "null_rating_reason": ""}}, {"item_type": "movie", "id": "1296794", "rank": 20, "name": "怪形", "names": [], "links": ["https://movie.douban.com/subject/1296794/", "douban://douban.com/movie/1296794"], "covers": ["https://img9.doubanio.com/view/photo/m_ratio_poster/public/p449608716.jpg", "https://img9.doubanio.com/view/photo/s_ratio_poster/public/p449608716.jpg"], "rating": {"count": 77374, "max": 10, "star_count": 4.0, "value": 8.2}, "score": 8.2, "vote": 77374, "summary": "1982 / 美国 / 科幻 悬疑 恐怖 / 约翰·卡朋特 / 库尔特·拉塞尔 威尔福德·布利姆雷", "ext": {"comment": "", "controversy_reason": "", "rank_value": 20, "pic": {"large": "https://img9.doubanio.com/view/photo/m_ratio_poster/public/p449608716.jpg", "normal": "https://img9.doubanio.com/view/photo/s_ratio_poster/public/p449608716.jpg"}, "is_show": false, "vendor_icons": ["https://img9.doubanio.com/f/frodo/fbc90f355fc45d5d2056e0d88c697f9414b56b44/pics/vendors/tencent.png", "https://img9.doubanio.com/f/frodo/6c7b857e6b2255201e73bf83732d95d572f3f9f7/pics/vendors/iqiyi.png"], "has_linewatch": true, "is_released": true, "interest": null, "color_scheme": {"is_dark": true, "primary_color_light": "7b8aa5", "_base_color": [0.6060606060606061, 0.25581395348837216, 0.16862745098039217], "secondary_color": "f4f6f9", "_avg_color": [0.6052631578947368, 0.2794117647058823, 0.5333333333333333], "primary_color_dark": "5e6a7f"}, "description": "", "tags": [], "cover_url": "https://img9.doubanio.com/view/photo/m_ratio_poster/public/p449608716.jpg", "photos": ["https://img1.doubanio.com/view/photo/m/public/p2232831818.jpg", "https://img1.doubanio.com/view/photo/m/public/p453665359.jpg", "https://img1.doubanio.com/view/photo/m/public/p2579641298.jpg", "https://img1.doubanio.com/view/photo/m/public/p2579641299.jpg"], "actions": ["可播放"], "sharing_url": "https://www.douban.com/doubanapp/dispatch/movie/1296794", "honor_infos": [{"kind": "movie", "uri": "douban://douban.com/subject_collection/ECGMORRUY?type=rank&category=movie&rank_type=film_genre", "rank": 20, "title": "美国恐怖片榜"}], "good_rating_stats": 0, "subtype": "movie", "null_rating_reason": ""}}]}