{"release_time": "2026-03-19T12:27:37+0800", "update_time": "2026-03-19T12:27:47+0800", "description": {"title": "豆瓣榜单", "subtitle": "加拿大爱情片榜", "source": "https://m.douban.com/subject_collection/ECEAOXFIQ", "link": "https://m.douban.com/rexxar/api/v2/subject_collection/ECEAOXFIQ/items", "page_start": 1, "page_end": 1, "page_total": 1, "page_limit": -1, "item_total": 20, "item_limit": 20, "page_count": 1, "sup_page_count": 0}, "extra": {"subject_type": "movie", "id": "ECEAOXFIQ", "name": "加拿大爱情片榜", "medium_name": "加拿大", "short_name": "爱情片", "total": 20}, "stats": {"movies": 20}, "movies": [{"item_type": "movie", "id": "2076181", "rank": 1, "name": "无姓之人", "names": [], "links": ["https://movie.douban.com/subject/2076181/", "douban://douban.com/movie/2076181"], "covers": ["https://img9.doubanio.com/view/photo/m_ratio_poster/public/p2133687605.jpg", "https://img9.doubanio.com/view/photo/s_ratio_poster/public/p2133687605.jpg"], "rating": {"count": 137807, "max": 10, "star_count": 4.0, "value": 8.2}, "score": 8.2, "vote": 137807, "summary": "2009 / 加拿大 比利时 法国 德国 / 剧情 爱情 科幻 奇幻 / 雅克·范·多梅尔 / 杰瑞德·莱托 莎拉·波利", "ext": {"comment": "", "controversy_reason": "", "rank_value": 1, "pic": {"large": "https://img9.doubanio.com/view/photo/m_ratio_poster/public/p2133687605.jpg", "normal": "https://img9.doubanio.com/view/photo/s_ratio_poster/public/p2133687605.jpg"}, "is_show": false, "vendor_icons": ["https://img9.doubanio.com/f/frodo/fbc90f355fc45d5d2056e0d88c697f9414b56b44/pics/vendors/tencent.png", "https://img9.doubanio.com/f/frodo/88a62f5e0cf9981c910e60f4421c3e66aac2c9bc/pics/vendors/bilibili.png", "https://img3.doubanio.com/f/frodo/6fa5caade3ca480ccd95f455ee4d195ee342eb90/pics/vendors/youku.png"], "has_linewatch": true, "is_released": true, "interest": null, "color_scheme": {"is_dark": true, "primary_color_light": "a5a1a1", "_base_color": [0.025252525252525304, 0.7764705882352941], "secondary_color": "f9f4f4", "_avg_color": [0.04635761589403976, 0.592156862745098], "primary_color_dark": "7f7c7c"}, "description": "", "tags": [], "cover_url": "https://img9.doubanio.com/view/photo/m_ratio_poster/public/p2133687605.jpg", "photos": ["https://img3.doubanio.com/view/photo/m/public/p502682967.jpg", "https://img1.doubanio.com/view/photo/m/public/p640654480.jpg", "https://img1.doubanio.com/view/photo/m/public/p2154998128.jpg", "https://img9.doubanio.com/view/photo/m/public/p502681604.jpg"], "actions": ["可播放"], "sharing_url": "https://www.douban.com/doubanapp/dispatch/movie/2076181", "honor_infos": [{"kind": "movie", "uri": "douban://douban.com/subject_collection/ECEAOXFIQ?type=rank&category=movie&rank_type=film_genre", "rank": 1, "title": "加拿大爱情片榜"}], "good_rating_stats": 0, "subtype": "movie", "null_rating_reason": ""}}, {"item_type": "movie", "id": "2212901", "rank": 2, "name": "平凡岁月的魅力", "names": [], "links": ["https://movie.douban.com/subject/2212901/", "douban://douban.com/movie/2212901"], "covers": ["https://img3.doubanio.com/view/photo/m_ratio_poster/public/p2453086907.jpg", "https://img3.doubanio.com/view/photo/s_ratio_poster/public/p2453086907.jpg"], "rating": {"count": 39505, "max": 10, "star_count": 4.0, "value": 8.4}, "score": 8.4, "vote": 39505, "summary": "2005 / 加拿大 美国 / 剧情 爱情 / 布兰特·席尔兹 / 凯丽·拉塞尔 斯基特·乌尔里奇", "ext": {"comment": "", "controversy_reason": "", "rank_value": 2, "pic": {"large": "https://img3.doubanio.com/view/photo/m_ratio_poster/public/p2453086907.jpg", "normal": "https://img3.doubanio.com/view/photo/s_ratio_poster/public/p2453086907.jpg"}, "is_show": false, "vendor_icons": [], "has_linewatch": false, "is_released": true, "interest": null, "color_scheme": {"is_dark": false, "primary_color_light": "f2e2d2", "_base_color": [0.08333333333333333, 0.12903225806451613, 0.9725490196078431], "secondary_color": "f9f7f4", "_avg_color": [0.07575757575757579, 0.13692946058091285, 0.9450980392156862], "primary_color_dark": "f2e2d2"}, "description": "", "tags": [], "cover_url": "https://img3.doubanio.com/view/photo/m_ratio_poster/public/p2453086907.jpg", "photos": ["https://img9.doubanio.com/view/photo/m/public/p2629078456.jpg", "https://img3.doubanio.com/view/photo/m/public/p2629078317.jpg", "https://img9.doubanio.com/view/photo/m/public/p2403577336.jpg", "https://img3.doubanio.com/view/photo/m/public/p2403577112.jpg"], "actions": [], "sharing_url": "https://www.douban.com/doubanapp/dispatch/movie/2212901", "honor_infos": [{"kind": "movie", "uri": "douban://douban.com/subject_collection/ECEAOXFIQ?type=rank&category=movie&rank_type=film_genre", "rank": 2, "title": "加拿大爱情片榜"}], "good_rating_stats": 0, "subtype": "movie", "null_rating_reason": ""}}, {"item_type": "movie", "id": "4838667", "rank": 3, "name": "双面劳伦斯", "names": [], "links": ["https://movie.douban.com/subject/4838667/", "douban://douban.com/movie/4838667"], "covers": ["https://img9.doubanio.com/view/photo/m_ratio_poster/public/p1878843375.jpg", "https://img9.doubanio.com/view/photo/s_ratio_poster/public/p1878843375.jpg"], "rating": {"count": 21313, "max": 10, "star_count": 4.0, "value": 8.0}, "score": 8.0, "vote": 21313, "summary": "2012 / 加拿大 法国 / 剧情 爱情 同性 / 泽维尔·多兰 / 梅尔维尔·珀波 苏珊娜·克莱蒙", "ext": {"comment": "", "controversy_reason": "", "rank_value": 3, "pic": {"large": "https://img9.doubanio.com/view/photo/m_ratio_poster/public/p1878843375.jpg", "normal": "https://img9.doubanio.com/view/photo/s_ratio_poster/public/p1878843375.jpg"}, "is_show": false, "vendor_icons": ["https://img9.doubanio.com/f/frodo/fbc90f355fc45d5d2056e0d88c697f9414b56b44/pics/vendors/tencent.png", "https://img2.doubanio.com/f/frodo/8e1b7f8b48804cf759fc411e75d62c5ffd4f8f42/pics/vendors/migu_video.png", "https://img9.doubanio.com/f/frodo/6c7b857e6b2255201e73bf83732d95d572f3f9f7/pics/vendors/iqiyi.png"], "has_linewatch": true, "is_released": true, "interest": null, "color_scheme": {"is_dark": true, "primary_color_light": "307269", "_base_color": [0.4776422764227642, 0.5815602836879432, 0.5529411764705883], "secondary_color": "f4f9f9", "_avg_color": [0.46610169491525427, 0.48360655737704916, 0.47843137254901963], "primary_color_dark": "204c46"}, "description": "", "tags": [], "cover_url": "https://img9.doubanio.com/view/photo/m_ratio_poster/public/p1878843375.jpg", "photos": ["https://img1.doubanio.com/view/photo/m/public/p2071497268.jpg", "https://img3.doubanio.com/view/photo/m/public/p1584078322.jpg", "https://img2.doubanio.com/view/photo/m/public/p1611353191.jpg", "https://img3.doubanio.com/view/photo/m/public/p2186019653.jpg"], "actions": ["可播放"], "sharing_url": "https://www.douban.com/doubanapp/dispatch/movie/4838667", "honor_infos": [{"kind": "movie", "uri": "douban://douban.com/subject_collection/ECEAOXFIQ?type=rank&category=movie&rank_type=film_genre", "rank": 3, "title": "加拿大爱情片榜"}], "good_rating_stats": 0, "subtype": "movie", "null_rating_reason": ""}}, {"item_type": "movie", "id": "3645150", "rank": 4, "name": "开罗时间", "names": [], "links": ["https://movie.douban.com/subject/3645150/", "douban://douban.com/movie/3645150"], "covers": ["https://img1.doubanio.com/view/photo/m_ratio_poster/public/p1505408000.jpg", "https://img1.doubanio.com/view/photo/s_ratio_poster/public/p1505408000.jpg"], "rating": {"count": 21770, "max": 10, "star_count": 4.0, "value": 7.9}, "score": 7.9, "vote": 21770, "summary": "2009 / 加拿大 爱尔兰 埃及 / 剧情 爱情 / 鲁巴·纳达 / 派翠西娅·克拉克森 亚历山大·希迪格", "ext": {"comment": "", "controversy_reason": "", "rank_value": 4, "pic": {"large": "https://img1.doubanio.com/view/photo/m_ratio_poster/public/p1505408000.jpg", "normal": "https://img1.doubanio.com/view/photo/s_ratio_poster/public/p1505408000.jpg"}, "is_show": false, "vendor_icons": ["https://img2.doubanio.com/f/frodo/8e1b7f8b48804cf759fc411e75d62c5ffd4f8f42/pics/vendors/migu_video.png", "https://img9.doubanio.com/f/frodo/fbc90f355fc45d5d2056e0d88c697f9414b56b44/pics/vendors/tencent.png", "https://img9.doubanio.com/f/frodo/88a62f5e0cf9981c910e60f4421c3e66aac2c9bc/pics/vendors/bilibili.png"], "has_linewatch": true, "is_released": true, "interest": null, "color_scheme": {"is_dark": true, "primary_color_light": "a59e87", "_base_color": [0.12500000000000006, 0.1841004184100419, 0.9372549019607843], "secondary_color": "f9f8f4", "_avg_color": [0.11702127659574464, 0.2361809045226131, 0.7803921568627451], "primary_color_dark": "7f7968"}, "description": "", "tags": [], "cover_url": "https://img1.doubanio.com/view/photo/m_ratio_poster/public/p1505408000.jpg", "photos": ["https://img3.doubanio.com/view/photo/m/public/p458351353.jpg", "https://img1.doubanio.com/view/photo/m/public/p458348649.jpg", "https://img9.doubanio.com/view/photo/m/public/p532520294.jpg", "https://img1.doubanio.com/view/photo/m/public/p458350608.jpg"], "actions": ["可播放"], "sharing_url": "https://www.douban.com/doubanapp/dispatch/movie/3645150", "honor_infos": [{"kind": "movie", "uri": "douban://douban.com/subject_collection/ECEAOXFIQ?type=rank&category=movie&rank_type=film_genre", "rank": 4, "title": "加拿大爱情片榜"}], "good_rating_stats": 0, "subtype": "movie", "null_rating_reason": ""}}, {"item_type": "movie", "id": "1296542", "rank": 5, "name": "铁达尼号沉没记", "names": [], "links": ["https://movie.douban.com/subject/1296542/", "douban://douban.com/movie/1296542"], "covers": ["https://img1.doubanio.com/view/photo/m_ratio_poster/public/p1502753588.jpg", "https://img1.doubanio.com/view/photo/s_ratio_poster/public/p1502753588.jpg"], "rating": {"count": 6892, "max": 10, "star_count": 4.5, "value": 8.6}, "score": 8.6, "vote": 6892, "summary": "1996 / 加拿大 美国 / 剧情 动作 爱情 历史 灾难 / 罗伯特·里伯曼 / 彼得·盖勒 凯瑟琳·泽塔-琼斯", "ext": {"comment": "", "controversy_reason": "", "rank_value": 5, "pic": {"large": "https://img1.doubanio.com/view/photo/m_ratio_poster/public/p1502753588.jpg", "normal": "https://img1.doubanio.com/view/photo/s_ratio_poster/public/p1502753588.jpg"}, "is_show": false, "vendor_icons": [], "has_linewatch": false, "is_released": true, "interest": null, "color_scheme": {"is_dark": true, "primary_color_light": "5c6672", "_base_color": [0.5952380952380952, 0.19444444444444445, 0.1411764705882353], "secondary_color": "f4f7f9", "_avg_color": [0.5833333333333334, 0.23636363636363641, 0.43137254901960786], "primary_color_dark": "3d444c"}, "description": "", "tags": [], "cover_url": "https://img1.doubanio.com/view/photo/m_ratio_poster/public/p1502753588.jpg", "photos": ["https://img3.doubanio.com/view/photo/m/public/p2187158202.jpg", "https://img3.doubanio.com/view/photo/m/public/p1502754343.jpg", "https://img3.doubanio.com/view/photo/m/public/p2681428563.jpg", "https://img3.doubanio.com/view/photo/m/public/p2681666747.jpg"], "actions": [], "sharing_url": "https://www.douban.com/doubanapp/dispatch/movie/1296542", "honor_infos": [{"kind": "movie", "uri": "douban://douban.com/subject_collection/ECHMOGZLQ?type=rank&category=movie&rank_type=film_genre", "rank": 1, "title": "冷门佳作灾难片榜"}], "good_rating_stats": 0, "subtype": "movie", "null_rating_reason": ""}}, {"item_type": "movie", "id": "4728076", "rank": 6, "name": "幻想之爱", "names": [], "links": ["https://movie.douban.com/subject/4728076/", "douban://douban.com/movie/4728076"], "covers": ["https://img1.doubanio.com/view/photo/m_ratio_poster/public/p699224369.jpg", "https://img1.doubanio.com/view/photo/s_ratio_poster/public/p699224369.jpg"], "rating": {"count": 17976, "max": 10, "star_count": 4.0, "value": 7.6}, "score": 7.6, "vote": 17976, "summary": "2010 / 加拿大 / 剧情 爱情 同性 / 泽维尔·多兰 / 泽维尔·多兰 莫妮亚·乔柯里", "ext": {"comment": "", "controversy_reason": "", "rank_value": 6, "pic": {"large": "https://img1.doubanio.com/view/photo/m_ratio_poster/public/p699224369.jpg", "normal": "https://img1.doubanio.com/view/photo/s_ratio_poster/public/p699224369.jpg"}, "is_show": false, "vendor_icons": [], "has_linewatch": false, "is_released": true, "interest": null, "color_scheme": {"is_dark": true, "primary_color_light": "a5031f", "_base_color": [0.9712121212121212, 0.9777777777777777, 0.8823529411764706], "secondary_color": "f9f4f5", "_avg_color": [0.9706867671691792, 0.9660194174757282, 0.807843137254902], "primary_color_dark": "7f0218"}, "description": "", "tags": [], "cover_url": "https://img1.doubanio.com/view/photo/m_ratio_poster/public/p699224369.jpg", "photos": ["https://img3.doubanio.com/view/photo/m/public/p469516267.jpg", "https://img2.doubanio.com/view/photo/m/public/p699235931.jpg", "https://img3.doubanio.com/view/photo/m/public/p699233383.jpg", "https://img9.doubanio.com/view/photo/m/public/p699233525.jpg"], "actions": [], "sharing_url": "https://www.douban.com/doubanapp/dispatch/movie/4728076", "honor_infos": [{"kind": "movie", "uri": "douban://douban.com/subject_collection/ECEAOXFIQ?type=rank&category=movie&rank_type=film_genre", "rank": 6, "title": "加拿大爱情片榜"}], "good_rating_stats": 0, "subtype": "movie", "null_rating_reason": ""}}, {"item_type": "movie", "id": "1441191", "rank": 7, "name": "水", "names": [], "links": ["https://movie.douban.com/subject/1441191/", "douban://douban.com/movie/1441191"], "covers": ["https://img1.doubanio.com/view/photo/m_ratio_poster/public/p1197911950.jpg", "https://img1.doubanio.com/view/photo/s_ratio_poster/public/p1197911950.jpg"], "rating": {"count": 6418, "max": 10, "star_count": 4.0, "value": 8.4}, "score": 8.4, "vote": 6418, "summary": "2005 / 加拿大 印度 / 剧情 爱情 / 迪帕·梅塔 / Lisa Ray John Abraham", "ext": {"comment": "", "controversy_reason": "", "rank_value": 7, "pic": {"large": "https://img1.doubanio.com/view/photo/m_ratio_poster/public/p1197911950.jpg", "normal": "https://img1.doubanio.com/view/photo/s_ratio_poster/public/p1197911950.jpg"}, "is_show": false, "vendor_icons": [], "has_linewatch": false, "is_released": true, "interest": null, "color_scheme": {"is_dark": true, "primary_color_light": "a59898", "_base_color": [0.08108108108108117, 0.1450980392156863], "secondary_color": "f9f4f4", "_avg_color": [0.07471264367816095, 0.17261904761904767, 0.6588235294117647], "primary_color_dark": "7f7575"}, "description": "", "tags": [], "cover_url": "https://img1.doubanio.com/view/photo/m_ratio_poster/public/p1197911950.jpg", "photos": ["https://img9.doubanio.com/view/photo/m/public/p1197913435.jpg", "https://img3.doubanio.com/view/photo/m/public/p1197918253.jpg", "https://img1.doubanio.com/view/photo/m/public/p1197915199.jpg", "https://img9.doubanio.com/view/photo/m/public/p1197913224.jpg"], "actions": [], "sharing_url": "https://www.douban.com/doubanapp/dispatch/movie/1441191", "honor_infos": [{"kind": "movie", "uri": "douban://douban.com/subject_collection/ECEAOXFIQ?type=rank&category=movie&rank_type=film_genre", "rank": 7, "title": "加拿大爱情片榜"}], "good_rating_stats": 0, "subtype": "movie", "null_rating_reason": ""}}, {"item_type": "movie", "id": "1293297", "rank": 8, "name": "孽扣", "names": [], "links": ["https://movie.douban.com/subject/1293297/", "douban://douban.com/movie/1293297"], "covers": ["https://img2.doubanio.com/view/photo/m_ratio_poster/public/p2187073171.jpg", "https://img2.doubanio.com/view/photo/s_ratio_poster/public/p2187073171.jpg"], "rating": {"count": 9414, "max": 10, "star_count": 4.0, "value": 7.8}, "score": 7.8, "vote": 9414, "summary": "1988 / 加拿大 / 剧情 爱情 惊悚 / 大卫·柯南伯格 / 杰瑞米·艾恩斯 詹妮薇芙·布卓", "ext": {"comment": "", "controversy_reason": "", "rank_value": 8, "pic": {"large": "https://img2.doubanio.com/view/photo/m_ratio_poster/public/p2187073171.jpg", "normal": "https://img2.doubanio.com/view/photo/s_ratio_poster/public/p2187073171.jpg"}, "is_show": false, "vendor_icons": [], "has_linewatch": false, "is_released": true, "interest": null, "color_scheme": {"is_dark": true, "primary_color_light": "707270", "_base_color": [0.3333333333333333, 0.01935483870967735, 0.6078431372549019], "secondary_color": "f4f9f4", "_avg_color": [0.055555555555555435, 0.06521739130434775, 0.3607843137254902], "primary_color_dark": "4b4c4b"}, "description": "", "tags": [], "cover_url": "https://img2.doubanio.com/view/photo/m_ratio_poster/public/p2187073171.jpg", "photos": ["https://img9.doubanio.com/view/photo/m/public/p2548299836.jpg", "https://img1.doubanio.com/view/photo/m/public/p2385490648.jpg", "https://img1.doubanio.com/view/photo/m/public/p2458539748.jpg", "https://img3.doubanio.com/view/photo/m/public/p2514522743.jpg"], "actions": [], "sharing_url": "https://www.douban.com/doubanapp/dispatch/movie/1293297", "honor_infos": [{"kind": "movie", "uri": "douban://douban.com/subject_collection/ECY4ODRSY?type=rank&category=movie&rank_type=film_genre", "rank": 7, "title": "冷门佳作惊悚片榜"}], "good_rating_stats": 0, "subtype": "movie", "null_rating_reason": ""}}, {"item_type": "movie", "id": "1308787", "rank": 9, "name": "成为朱莉娅", "names": [], "links": ["https://movie.douban.com/subject/1308787/", "douban://douban.com/movie/1308787"], "covers": ["https://img9.doubanio.com/view/photo/m_ratio_poster/public/p825998395.jpg", "https://img9.doubanio.com/view/photo/s_ratio_poster/public/p825998395.jpg"], "rating": {"count": 7561, "max": 10, "star_count": 4.0, "value": 8.0}, "score": 8.0, "vote": 7561, "summary": "2004 / 加拿大 匈牙利 英国 美国 / 剧情 喜剧 爱情 / 伊斯特凡·萨博 / 安妮特·贝宁 肖恩·埃文斯", "ext": {"comment": "", "controversy_reason": "", "rank_value": 9, "pic": {"large": "https://img9.doubanio.com/view/photo/m_ratio_poster/public/p825998395.jpg", "normal": "https://img9.doubanio.com/view/photo/s_ratio_poster/public/p825998395.jpg"}, "is_show": false, "vendor_icons": [], "has_linewatch": false, "is_released": true, "interest": null, "color_scheme": {"is_dark": true, "primary_color_light": "a5765e", "_base_color": [0.05555555555555556, 0.42857142857142855, 0.08235294117647059], "secondary_color": "f9f6f4", "_avg_color": [0.1068376068376068, 0.5909090909090909, 0.5176470588235295], "primary_color_dark": "7f5b48"}, "description": "", "tags": [], "cover_url": "https://img9.doubanio.com/view/photo/m_ratio_poster/public/p825998395.jpg", "photos": ["https://img1.doubanio.com/view/photo/m/public/p886041788.jpg", "https://img3.doubanio.com/view/photo/m/public/p886049117.jpg", "https://img9.doubanio.com/view/photo/m/public/p2462756185.jpg", "https://img1.doubanio.com/view/photo/m/public/p886039359.jpg"], "actions": [], "sharing_url": "https://www.douban.com/doubanapp/dispatch/movie/1308787", "honor_infos": [{"kind": "movie", "uri": "douban://douban.com/subject_collection/ECEAOXFIQ?type=rank&category=movie&rank_type=film_genre", "rank": 9, "title": "加拿大爱情片榜"}], "good_rating_stats": 0, "subtype": "movie", "null_rating_reason": ""}}, {"item_type": "movie", "id": "1420010", "rank": 10, "name": "没有我的日子", "names": [], "links": ["https://movie.douban.com/subject/1420010/", "douban://douban.com/movie/1420010"], "covers": ["https://img1.doubanio.com/view/photo/m_ratio_poster/public/p563068558.jpg", "https://img1.doubanio.com/view/photo/s_ratio_poster/public/p563068558.jpg"], "rating": {"count": 6181, "max": 10, "star_count": 4.0, "value": 7.9}, "score": 7.9, "vote": 6181, "summary": "2003 / 加拿大 西班牙 / 剧情 爱情 / 伊莎贝尔·科赛特 / 莎拉·波利 阿曼达·普拉莫", "ext": {"comment": "", "controversy_reason": "", "rank_value": 10, "pic": {"large": "https://img1.doubanio.com/view/photo/m_ratio_poster/public/p563068558.jpg", "normal": "https://img1.doubanio.com/view/photo/s_ratio_poster/public/p563068558.jpg"}, "is_show": false, "vendor_icons": [], "has_linewatch": false, "is_released": true, "interest": null, "color_scheme": {"is_dark": true, "primary_color_light": "722d32", "_base_color": [0.9886363636363636, 0.6027397260273973, 0.28627450980392155], "secondary_color": "f9f4f5", "_avg_color": [0.013071895424836591, 0.4811320754716981, 0.41568627450980394], "primary_color_dark": "4c1e21"}, "description": "", "tags": [], "cover_url": "https://img1.doubanio.com/view/photo/m_ratio_poster/public/p563068558.jpg", "photos": ["https://img3.doubanio.com/view/photo/m/public/p563035173.jpg", "https://img1.doubanio.com/view/photo/m/public/p626529790.jpg", "https://img1.doubanio.com/view/photo/m/public/p563035408.jpg", "https://img3.doubanio.com/view/photo/m/public/p563035012.jpg"], "actions": [], "sharing_url": "https://www.douban.com/doubanapp/dispatch/movie/1420010", "honor_infos": [{"kind": "movie", "uri": "douban://douban.com/subject_collection/ECEAOXFIQ?type=rank&category=movie&rank_type=film_genre", "rank": 10, "title": "加拿大爱情片榜"}], "good_rating_stats": 0, "subtype": "movie", "null_rating_reason": ""}}, {"item_type": "movie", "id": "30389671", "rank": 11, "name": "最幸福的季节", "names": [], "links": ["https://movie.douban.com/subject/30389671/", "douban://douban.com/movie/30389671"], "covers": ["https://img2.doubanio.com/view/photo/m_ratio_poster/public/p2625245511.jpg", "https://img2.doubanio.com/view/photo/s_ratio_poster/public/p2625245511.jpg"], "rating": {"count": 23348, "max": 10, "star_count": 3.5, "value": 7.0}, "score": 7.0, "vote": 23348, "summary": "2020 / 加拿大 美国 / 爱情 同性 / 克里·杜瓦尔 / 克里斯汀·斯图尔特 麦肯兹·戴维斯", "ext": {"comment": "", "controversy_reason": "", "rank_value": 11, "pic": {"large": "https://img2.doubanio.com/view/photo/m_ratio_poster/public/p2625245511.jpg", "normal": "https://img2.doubanio.com/view/photo/s_ratio_poster/public/p2625245511.jpg"}, "is_show": false, "vendor_icons": [], "has_linewatch": false, "is_released": true, "interest": null, "color_scheme": {"is_dark": true, "primary_color_light": "a59173", "_base_color": [0.09946236559139787, 0.30243902439024395, 0.803921568627451], "secondary_color": "f9f7f4", "_avg_color": [0.07711442786069649, 0.40119760479041916, 0.6549019607843137], "primary_color_dark": "7f6f58"}, "description": "", "tags": [], "cover_url": "https://img2.doubanio.com/view/photo/m_ratio_poster/public/p2625245511.jpg", "photos": ["https://img1.doubanio.com/view/photo/m/public/p2626043470.jpg", "https://img9.doubanio.com/view/photo/m/public/p2611058274.jpg", "https://img3.doubanio.com/view/photo/m/public/p2625263592.jpg", "https://img1.doubanio.com/view/photo/m/public/p2619159290.jpg"], "actions": [], "sharing_url": "https://www.douban.com/doubanapp/dispatch/movie/30389671", "honor_infos": [{"kind": "movie", "uri": "douban://douban.com/subject_collection/ECEAOXFIQ?type=rank&category=movie&rank_type=film_genre", "rank": 11, "title": "加拿大爱情片榜"}], "good_rating_stats": 0, "subtype": "movie", "null_rating_reason": ""}}, {"item_type": "movie", "id": "1308764", "rank": 12, "name": "灰姑娘的故事", "names": [], "links": ["https://movie.douban.com/subject/1308764/", "douban://douban.com/movie/1308764"], "covers": ["https://img9.doubanio.com/view/photo/m_ratio_poster/public/p802390374.jpg", "https://img9.doubanio.com/view/photo/s_ratio_poster/public/p802390374.jpg"], "rating": {"count": 51472, "max": 10, "star_count": 3.5, "value": 6.8}, "score": 6.8, "vote": 51472, "summary": "2004 / 加拿大 美国 / 喜剧 爱情 家庭 / Mark Rosman / 希拉里·达芙 詹妮佛·库里奇", "ext": {"comment": "", "controversy_reason": "", "rank_value": 12, "pic": {"large": "https://img9.doubanio.com/view/photo/m_ratio_poster/public/p802390374.jpg", "normal": "https://img9.doubanio.com/view/photo/s_ratio_poster/public/p802390374.jpg"}, "is_show": false, "vendor_icons": ["https://img2.doubanio.com/f/frodo/8e1b7f8b48804cf759fc411e75d62c5ffd4f8f42/pics/vendors/migu_video.png", "https://img9.doubanio.com/f/frodo/fbc90f355fc45d5d2056e0d88c697f9414b56b44/pics/vendors/tencent.png", "https://img3.doubanio.com/f/frodo/6fa5caade3ca480ccd95f455ee4d195ee342eb90/pics/vendors/youku.png"], "has_linewatch": true, "is_released": true, "interest": null, "color_scheme": {"is_dark": true, "primary_color_light": "6986a5", "_base_color": [0.5857142857142857, 0.36082474226804123, 0.3803921568627451], "secondary_color": "f4f7f9", "_avg_color": [0.6111111111111102, 0.013513513513513592, 0.8705882352941177], "primary_color_dark": "51677f"}, "description": "", "tags": [], "cover_url": "https://img9.doubanio.com/view/photo/m_ratio_poster/public/p802390374.jpg", "photos": ["https://img2.doubanio.com/view/photo/m/public/p456273071.jpg", "https://img9.doubanio.com/view/photo/m/public/p660546046.jpg", "https://img2.doubanio.com/view/photo/m/public/p456272921.jpg", "https://img9.doubanio.com/view/photo/m/public/p1300737276.jpg"], "actions": ["可播放"], "sharing_url": "https://www.douban.com/doubanapp/dispatch/movie/1308764", "honor_infos": [{"kind": "movie", "uri": "douban://douban.com/subject_collection/ECEAOXFIQ?type=rank&category=movie&rank_type=film_genre", "rank": 12, "title": "加拿大爱情片榜"}], "good_rating_stats": 0, "subtype": "movie", "null_rating_reason": ""}}, {"item_type": "movie", "id": "1301148", "rank": 13, "name": "野蛮入侵", "names": [], "links": ["https://movie.douban.com/subject/1301148/", "douban://douban.com/movie/1301148"], "covers": ["https://img2.doubanio.com/view/photo/m_ratio_poster/public/p2368536301.jpg", "https://img2.doubanio.com/view/photo/s_ratio_poster/public/p2368536301.jpg"], "rating": {"count": 5878, "max": 10, "star_count": 4.0, "value": 7.7}, "score": 7.7, "vote": 5878, "summary": "2003 / 加拿大 法国 / 剧情 喜剧 爱情 悬疑 犯罪 / 德尼·阿尔康 / 雷米·吉拉德 斯蒂芬·卢梭", "ext": {"comment": "", "controversy_reason": "", "rank_value": 13, "pic": {"large": "https://img2.doubanio.com/view/photo/m_ratio_poster/public/p2368536301.jpg", "normal": "https://img2.doubanio.com/view/photo/s_ratio_poster/public/p2368536301.jpg"}, "is_show": false, "vendor_icons": ["https://img9.doubanio.com/f/frodo/6c7b857e6b2255201e73bf83732d95d572f3f9f7/pics/vendors/iqiyi.png"], "has_linewatch": true, "is_released": true, "interest": null, "color_scheme": {"is_dark": true, "primary_color_light": "4289a5", "_base_color": [0.5481481481481482, 0.5960264900662251, 0.592156862745098], "secondary_color": "f4f8f9", "_avg_color": [0.5289855072463769, 0.1393939393939394, 0.6470588235294118], "primary_color_dark": "33697f"}, "description": "", "tags": [], "cover_url": "https://img2.doubanio.com/view/photo/m_ratio_poster/public/p2368536301.jpg", "photos": ["https://img3.doubanio.com/view/photo/m/public/p2368536403.jpg", "https://img2.doubanio.com/view/photo/m/public/p2368536401.jpg", "https://img9.doubanio.com/view/photo/m/public/p2368536394.jpg", "https://img3.doubanio.com/view/photo/m/public/p2368536393.jpg"], "actions": ["可播放"], "sharing_url": "https://www.douban.com/doubanapp/dispatch/movie/1301148", "honor_infos": [{"kind": "movie", "uri": "douban://douban.com/subject_collection/ECYMPDCTI?type=rank&category=movie&rank_type=film_genre", "rank": 13, "title": "加拿大悬疑片榜"}], "good_rating_stats": 0, "subtype": "movie", "null_rating_reason": ""}}, {"item_type": "movie", "id": "1292485", "rank": 14, "name": "男情难了", "names": [], "links": ["https://movie.douban.com/subject/1292485/", "douban://douban.com/movie/1292485"], "covers": ["https://img1.doubanio.com/view/photo/m_ratio_poster/public/p1247013369.jpg", "https://img1.doubanio.com/view/photo/s_ratio_poster/public/p1247013369.jpg"], "rating": {"count": 3708, "max": 10, "star_count": 4.0, "value": 8.2}, "score": 8.2, "vote": 3708, "summary": "1996 / 加拿大 / 剧情 爱情 同性 奇幻 / 约翰·葛雷森 / 丹尼·吉尔摩尔 Jason Cadieux", "ext": {"comment": "", "controversy_reason": "", "rank_value": 14, "pic": {"large": "https://img1.doubanio.com/view/photo/m_ratio_poster/public/p1247013369.jpg", "normal": "https://img1.doubanio.com/view/photo/s_ratio_poster/public/p1247013369.jpg"}, "is_show": false, "vendor_icons": [], "has_linewatch": false, "is_released": true, "interest": null, "color_scheme": {"is_dark": true, "primary_color_light": "a53f30", "_base_color": [0.02179487179487179, 0.7065217391304347, 0.7215686274509804], "secondary_color": "f9f5f4", "_avg_color": [0.05284552845528456, 0.640625, 0.7529411764705882], "primary_color_dark": "7f3125"}, "description": "", "tags": [], "cover_url": "https://img1.doubanio.com/view/photo/m_ratio_poster/public/p1247013369.jpg", "photos": ["https://img2.doubanio.com/view/photo/m/public/p2221713861.jpg", "https://img1.doubanio.com/view/photo/m/public/p2503855889.jpg", "https://img1.doubanio.com/view/photo/m/public/p816377639.jpg", "https://img3.doubanio.com/view/photo/m/public/p2503856607.jpg"], "actions": [], "sharing_url": "https://www.douban.com/doubanapp/dispatch/movie/1292485", "honor_infos": [{"kind": "movie", "uri": "douban://douban.com/subject_collection/ECEAOXFIQ?type=rank&category=movie&rank_type=film_genre", "rank": 14, "title": "加拿大爱情片榜"}], "good_rating_stats": 0, "subtype": "movie", "null_rating_reason": ""}}, {"item_type": "movie", "id": "1302391", "rank": 15, "name": "夜幕低垂", "names": [], "links": ["https://movie.douban.com/subject/1302391/", "douban://douban.com/movie/1302391"], "covers": ["https://img9.doubanio.com/view/photo/m_ratio_poster/public/p1514688046.jpg", "https://img9.doubanio.com/view/photo/s_ratio_poster/public/p1514688046.jpg"], "rating": {"count": 5815, "max": 10, "star_count": 3.5, "value": 7.3}, "score": 7.3, "vote": 5815, "summary": "1995 / 加拿大 / 剧情 爱情 同性 / 帕特丽夏·罗兹玛 / 帕斯卡·比西埃尔 瑞秋·克劳福德", "ext": {"comment": "", "controversy_reason": "", "rank_value": 15, "pic": {"large": "https://img9.doubanio.com/view/photo/m_ratio_poster/public/p1514688046.jpg", "normal": "https://img9.doubanio.com/view/photo/s_ratio_poster/public/p1514688046.jpg"}, "is_show": false, "vendor_icons": [], "has_linewatch": false, "is_released": true, "interest": null, "color_scheme": {"is_dark": true, "primary_color_light": "72442f", "_base_color": [0.051388888888888894, 0.5853658536585367, 0.803921568627451], "secondary_color": "f9f6f4", "_avg_color": [0.020325203252032503, 0.640625, 0.25098039215686274], "primary_color_dark": "4c2d1f"}, "description": "", "tags": [], "cover_url": "https://img9.doubanio.com/view/photo/m_ratio_poster/public/p1514688046.jpg", "photos": ["https://img1.doubanio.com/view/photo/m/public/p2179929208.jpg", "https://img1.doubanio.com/view/photo/m/public/p2179929229.jpg", "https://img1.doubanio.com/view/photo/m/public/p1287239940.jpg", "https://img1.doubanio.com/view/photo/m/public/p2179928929.jpg"], "actions": [], "sharing_url": "https://www.douban.com/doubanapp/dispatch/movie/1302391", "honor_infos": [{"kind": "movie", "uri": "douban://douban.com/subject_collection/ECEAOXFIQ?type=rank&category=movie&rank_type=film_genre", "rank": 15, "title": "加拿大爱情片榜"}], "good_rating_stats": 0, "subtype": "movie", "null_rating_reason": ""}}, {"item_type": "movie", "id": "3153991", "rank": 16, "name": "年轻的女王", "names": [], "links": ["https://movie.douban.com/subject/3153991/", "douban://douban.com/movie/3153991"], "covers": ["https://img3.doubanio.com/view/photo/m_ratio_poster/public/p2292224232.jpg", "https://img3.doubanio.com/view/photo/s_ratio_poster/public/p2292224232.jpg"], "rating": {"count": 5661, "max": 10, "star_count": 3.5, "value": 7.2}, "score": 7.2, "vote": 5661, "summary": "2015 / 加拿大 芬兰 法国 德国 瑞典 / 剧情 爱情 同性 传记 / 米卡·考里斯马基 / 玛琳·布斯卡 莎拉·加顿", "ext": {"comment": "", "controversy_reason": "", "rank_value": 16, "pic": {"large": "https://img3.doubanio.com/view/photo/m_ratio_poster/public/p2292224232.jpg", "normal": "https://img3.doubanio.com/view/photo/s_ratio_poster/public/p2292224232.jpg"}, "is_show": false, "vendor_icons": [], "has_linewatch": false, "is_released": true, "interest": null, "color_scheme": {"is_dark": true, "primary_color_light": "725f59", "_base_color": [0.041666666666666664, 0.2222222222222222, 0.1411764705882353], "secondary_color": "f9f6f4", "_avg_color": [0.06666666666666667, 0.2631578947368421, 0.2980392156862745], "primary_color_dark": "4c3f3b"}, "description": "", "tags": [], "cover_url": "https://img3.doubanio.com/view/photo/m_ratio_poster/public/p2292224232.jpg", "photos": ["https://img1.doubanio.com/view/photo/m/public/p2882113430.jpg", "https://img9.doubanio.com/view/photo/m/public/p2175715494.jpg", "https://img3.doubanio.com/view/photo/m/public/p2288924107.jpg", "https://img9.doubanio.com/view/photo/m/public/p2288924115.jpg"], "actions": [], "sharing_url": "https://www.douban.com/doubanapp/dispatch/movie/3153991", "honor_infos": [{"kind": "movie", "uri": "douban://douban.com/subject_collection/ECEAOXFIQ?type=rank&category=movie&rank_type=film_genre", "rank": 16, "title": "加拿大爱情片榜"}], "good_rating_stats": 0, "subtype": "movie", "null_rating_reason": ""}}, {"item_type": "movie", "id": "1297287", "rank": 17, "name": "意乱情迷", "names": [], "links": ["https://movie.douban.com/subject/1297287/", "douban://douban.com/movie/1297287"], "covers": ["https://img2.doubanio.com/view/photo/m_ratio_poster/public/p2527744011.jpg", "https://img2.doubanio.com/view/photo/s_ratio_poster/public/p2527744011.jpg"], "rating": {"count": 5512, "max": 10, "star_count": 3.5, "value": 7.2}, "score": 7.2, "vote": 5512, "summary": "2001 / 加拿大 / 剧情 爱情 同性 / 派珀·佩拉博 Jessica Pare", "ext": {"comment": "", "controversy_reason": "", "rank_value": 17, "pic": {"large": "https://img2.doubanio.com/view/photo/m_ratio_poster/public/p2527744011.jpg", "normal": "https://img2.doubanio.com/view/photo/s_ratio_poster/public/p2527744011.jpg"}, "is_show": false, "vendor_icons": [], "has_linewatch": false, "is_released": true, "interest": null, "color_scheme": {"is_dark": true, "primary_color_light": "72574e", "_base_color": [0.0390625, 0.31527093596059114, 0.796078431372549], "secondary_color": "f9f6f4", "_avg_color": [0.5333333333333332, 0.10416666666666659, 0.18823529411764706], "primary_color_dark": "4c3a34"}, "description": "", "tags": [], "cover_url": "https://img2.doubanio.com/view/photo/m_ratio_poster/public/p2527744011.jpg", "photos": ["https://img3.doubanio.com/view/photo/m/public/p1791495997.jpg", "https://img3.doubanio.com/view/photo/m/public/p1791496273.jpg", "https://img3.doubanio.com/view/photo/m/public/p1791496662.jpg", "https://img9.doubanio.com/view/photo/m/public/p1791496614.jpg"], "actions": [], "sharing_url": "https://www.douban.com/doubanapp/dispatch/movie/1297287", "honor_infos": [{"kind": "movie", "uri": "douban://douban.com/subject_collection/ECEAOXFIQ?type=rank&category=movie&rank_type=film_genre", "rank": 17, "title": "加拿大爱情片榜"}], "good_rating_stats": 0, "subtype": "movie", "null_rating_reason": ""}}, {"item_type": "movie", "id": "1578500", "rank": 18, "name": "绢", "names": [], "links": ["https://movie.douban.com/subject/1578500/", "douban://douban.com/movie/1578500"], "covers": ["https://img1.doubanio.com/view/photo/m_ratio_poster/public/p794911239.jpg", "https://img1.doubanio.com/view/photo/s_ratio_poster/public/p794911239.jpg"], "rating": {"count": 8730, "max": 10, "star_count": 3.5, "value": 6.9}, "score": 6.9, "vote": 8730, "summary": "2007 / 加拿大 法国 意大利 英国 日本 / 剧情 爱情 / 弗朗索瓦·吉拉德 / 芦名星 迈克尔·皮特", "ext": {"comment": "", "controversy_reason": "", "rank_value": 18, "pic": {"large": "https://img1.doubanio.com/view/photo/m_ratio_poster/public/p794911239.jpg", "normal": "https://img1.doubanio.com/view/photo/s_ratio_poster/public/p794911239.jpg"}, "is_show": false, "vendor_icons": [], "has_linewatch": false, "is_released": true, "interest": null, "color_scheme": {"is_dark": true, "primary_color_light": "a59783", "_base_color": [0.09574468085106379, 0.2052401746724891, 0.8980392156862745], "secondary_color": "f9f7f4", "_avg_color": [0.08333333333333333, 0.2464454976303317, 0.8274509803921568], "primary_color_dark": "7f7465"}, "description": "", "tags": [], "cover_url": "https://img1.doubanio.com/view/photo/m_ratio_poster/public/p794911239.jpg", "photos": ["https://img9.doubanio.com/view/photo/m/public/p457036774.jpg", "https://img2.doubanio.com/view/photo/m/public/p457036731.jpg", "https://img3.doubanio.com/view/photo/m/public/p725314142.jpg", "https://img3.doubanio.com/view/photo/m/public/p725314322.jpg"], "actions": [], "sharing_url": "https://www.douban.com/doubanapp/dispatch/movie/1578500", "honor_infos": [{"kind": "movie", "uri": "douban://douban.com/subject_collection/ECEAOXFIQ?type=rank&category=movie&rank_type=film_genre", "rank": 18, "title": "加拿大爱情片榜"}], "good_rating_stats": 0, "subtype": "movie", "null_rating_reason": ""}}, {"item_type": "movie", "id": "1939652", "rank": 19, "name": "搞错人", "names": [], "links": ["https://movie.douban.com/subject/1939652/", "douban://douban.com/movie/1939652"], "covers": ["https://img3.doubanio.com/view/photo/m_ratio_poster/public/p2533660053.jpg", "https://img3.doubanio.com/view/photo/s_ratio_poster/public/p2533660053.jpg"], "rating": {"count": 3814, "max": 10, "star_count": 3.5, "value": 7.4}, "score": 7.4, "vote": 3814, "summary": "1997 / 加拿大 英国 / 喜剧 爱情 惊悚 / 大卫·斯坦伯格 / 戴夫·弗利 詹妮弗·提莉", "ext": {"comment": "", "controversy_reason": "", "rank_value": 19, "pic": {"large": "https://img3.doubanio.com/view/photo/m_ratio_poster/public/p2533660053.jpg", "normal": "https://img3.doubanio.com/view/photo/s_ratio_poster/public/p2533660053.jpg"}, "is_show": false, "vendor_icons": [], "has_linewatch": false, "is_released": true, "interest": null, "color_scheme": {"is_dark": true, "primary_color_light": "9ca5a5", "_base_color": [0.5, 0.057692307692307626, 0.20392156862745098], "secondary_color": "f4f9f9", "_avg_color": [0.01851851851851845, 0.04736842105263156, 0.7450980392156863], "primary_color_dark": "787f7f"}, "description": "", "tags": [], "cover_url": "https://img3.doubanio.com/view/photo/m_ratio_poster/public/p2533660053.jpg", "photos": ["https://img1.doubanio.com/view/photo/m/public/p2619042529.jpg", "https://img1.doubanio.com/view/photo/m/public/p2619042540.jpg", "https://img3.doubanio.com/view/photo/m/public/p2619042513.jpg", "https://img1.doubanio.com/view/photo/m/public/p2619042490.jpg"], "actions": [], "sharing_url": "https://www.douban.com/doubanapp/dispatch/movie/1939652", "honor_infos": [{"kind": "movie", "uri": "douban://douban.com/subject_collection/ECEAOXFIQ?type=rank&category=movie&rank_type=film_genre", "rank": 19, "title": "加拿大爱情片榜"}], "good_rating_stats": 0, "subtype": "movie", "null_rating_reason": ""}}, {"item_type": "movie", "id": "25772380", "rank": 20, "name": "哥本哈根", "names": [], "links": ["https://movie.douban.com/subject/25772380/", "douban://douban.com/movie/25772380"], "covers": ["https://img3.doubanio.com/view/photo/m_ratio_poster/public/p2213973257.jpg", "https://img3.doubanio.com/view/photo/s_ratio_poster/public/p2213973257.jpg"], "rating": {"count": 3506, "max": 10, "star_count": 3.5, "value": 7.3}, "score": 7.3, "vote": 3506, "summary": "2014 / 加拿大 美国 丹麦 / 剧情 爱情 冒险 / Mark Raso / 格辛·安东尼 塔姆金·莫钦特", "ext": {"comment": "", "controversy_reason": "", "rank_value": 20, "pic": {"large": "https://img3.doubanio.com/view/photo/m_ratio_poster/public/p2213973257.jpg", "normal": "https://img3.doubanio.com/view/photo/s_ratio_poster/public/p2213973257.jpg"}, "is_show": false, "vendor_icons": [], "has_linewatch": false, "is_released": true, "interest": null, "color_scheme": {"is_dark": true, "primary_color_light": "3f5a72", "_base_color": [0.578125, 0.4444444444444444, 0.2823529411764706], "secondary_color": "f4f7f9", "_avg_color": [0.47222222222222193, 0.05263157894736848, 0.4470588235294118], "primary_color_dark": "2a3c4c"}, "description": "", "tags": [], "cover_url": "https://img3.doubanio.com/view/photo/m_ratio_poster/public/p2213973257.jpg", "photos": ["https://img1.doubanio.com/view/photo/m/public/p2228068509.jpg", "https://img1.doubanio.com/view/photo/m/public/p2228068408.jpg", "https://img1.doubanio.com/view/photo/m/public/p2230026389.jpg", "https://img1.doubanio.com/view/photo/m/public/p2530695618.jpg"], "actions": [], "sharing_url": "https://www.douban.com/doubanapp/dispatch/movie/25772380", "honor_infos": [{"kind": "movie", "uri": "douban://douban.com/subject_collection/ECEAOXFIQ?type=rank&category=movie&rank_type=film_genre", "rank": 20, "title": "加拿大爱情片榜"}], "good_rating_stats": 0, "subtype": "movie", "null_rating_reason": ""}}]}